mainframer/__about__.py
mainframer/__init__.py
mainframer/__main__.py
mainframer/activate_environment.py
mainframer/build.py
mainframer/install_cobols.py
mainframer/manage_config.py
mainframer/manage_environments.py
mainframer-0.2.0.dist-info/LICENSE
mainframer-0.2.0.dist-info/METADATA
mainframer-0.2.0.dist-info/WHEEL
mainframer-0.2.0.dist-info/entry_points.txt
mainframer-0.2.0.dist-info/RECORD
