Metadata-Version: 2.1
Name: mainframer
Version: 0.2.0
Summary: GnuCOBOL environment and package manager.
Home-page: https://github.com/matthewdeanmartin/mainframer
License: MIT
Keywords: cobol,gnucobol
Author: Matthew Martin
Author-email: matthewdeanmartin@gmail.com
Requires-Python: >=3.8
Classifier: Development Status :: 4 - Beta
Classifier: Intended Audience :: Developers
Classifier: License :: OSI Approved :: MIT License
Classifier: Operating System :: OS Independent
Classifier: Programming Language :: Python
Classifier: Programming Language :: Python :: 3
Classifier: Programming Language :: Python :: 3.8
Classifier: Programming Language :: Python :: 3.9
Classifier: Programming Language :: Python :: 3.10
Classifier: Programming Language :: Python :: 3.11
Classifier: Programming Language :: Python :: 3.12
Classifier: Programming Language :: Python :: 3.13
Requires-Dist: httpx (>=0.28.1)
Requires-Dist: requests (>=2.32.3)
Requires-Dist: rich (>=13.9.4)
Requires-Dist: shellingham (>=1.5.4)
Requires-Dist: toml (>=0.10.2)
Requires-Dist: tomli-w
Project-URL: Bug Tracker, https://github.com/matthewdeanmartin/mainframer/issues
Project-URL: Change Log, https://github.com/matthewdeanmartin/mainframer/blob/main/CHANGELOG.md
Project-URL: Documentation, https://matthewdeanmartin.github.io/mainframer/mainframer/index.html
Project-URL: Repository, https://github.com/matthewdeanmartin/mainframer
